README.txt
setup.cfg
setup.py
src/tstables/__init__.py
src/tstables/_version.py
src/tstables/benchmark.py
src/tstables/file.py
src/tstables/group.py
src/tstables/tstable.py
src/tstables.egg-info/PKG-INFO
src/tstables.egg-info/SOURCES.txt
src/tstables.egg-info/dependency_links.txt
src/tstables.egg-info/entry_points.txt
src/tstables.egg-info/requires.txt
src/tstables.egg-info/top_level.txt
src/tstables.egg-info/zip-safe