Metadata-Version: 1.0
Name: tstables
Version: 0.0.10
Summary: Handles large time series using PyTables and Pandas
Home-page: http://github.com/afiedler/tstables
Author: Andy Fiedler
Author-email: andy@andyfiedler.com
License: MIT
Keywords: time series high frequency HDF5
Platform: UNKNOWN
